netops/__init__.py
netops/__version__.py
netops/api/__init__.py
netops/api/monipe/__init__.py
netops/api/monipe/homologation_manager.py
netops/api/monipe/homologation_requester.py
netops/api/netbox/__init__.py
netops/api/netbox/inventory_plugin.py
netops/api/netbox/netbox_manager.py
netops/api/netbox/util.py
netops/api/zabbix/__init__.py
netops/api/zabbix/zabbix.py
netops/configs/__init__.py
netops/configs/apply_devices_configuration.py
netops/configs/configs.py
netops/configs/configuration_generator.py
netops/configs/get_configs.py
netops/configs/models.py
netops/configs/remote_commands.py
netops/configs/tests.py
netops/digital_twin/__init__.py
netops/digital_twin/configuration_generator.py
netops/digital_twin/models.py
netops/digital_twin/port_mapping.py
netops/infra/__init__.py
netops/infra/infra.py
netops/utils/__init__.py
netops/utils/databases.py
netops/utils/email.py
netops/utils/env_variables.py
netops/utils/monipe_requests.py
netops/utils/paths.py
netops/utils/template_rendering.py
netops/utils/utils.py
netops/validation_tests/__init__.py
netops/validation_tests/device_tests.py
netops/validation_tests/reachability.py
netops/validation_tests/service_tests.py
netops/validation_tests/traceroute.py
netops/validation_tests/junos/__init__.py
netops/validation_tests/junos/tests.py
netops-0.3.0.dist-info/LICENSE
netops-0.3.0.dist-info/METADATA
netops-0.3.0.dist-info/WHEEL
netops-0.3.0.dist-info/top_level.txt
netops-0.3.0.dist-info/RECORD
